MANIFEST.in
README.rst
setup.py
random_name/__init__.py
random_name.egg-info/PKG-INFO
random_name.egg-info/SOURCES.txt
random_name.egg-info/dependency_links.txt
random_name.egg-info/top_level.txt
random_name/dictionaries/__init__.py
random_name/dictionaries/adjectives.py
random_name/dictionaries/animals.py
random_name/dictionaries/colors.py