Metadata-Version: 1.1
Name: random-name
Version: 0.1.0
Summary: Simple tool for generating random names.
Home-page: https://github.com/phobologic/random_name
Author: Michael Barrett
Author-email: loki77@gmail.com
License: New BSD license
Platform: UNKNOWN
Classifier: Intended Audience :: Developers
Classifier: Natural Language :: English
Classifier: Programming Language :: Python :: 2
Classifier: License :: OSI Approved :: BSD License
Classifier: Development Status :: 3 - Alpha
